{
    "name": "level_00",
    "exits": [[12, 4, "right", "level_01"]],
    "back": [0,195,6],
    "size": [13, 8],
    "player": [0, 3],
    "enemies": [
        {
            "size": 1.1,
            "pic": "enemy_00",
            "speed": 5,
            "track": [
                [3, 0],
                [5, 0],
                [5, 2],
                [11, 2],
                [11, 6],
                [9, 6],
                [8, 7],
                [3, 4]
            ],
            "lives": 3,
            "snd": "enemy_00_snd"
        }    
    ],
    "map": {
        "tree": [
            1,
            1,
            [0, 0],
            [0, 1],
            [0, 5],
            [0, 6],
            [0, 7],
            [1, 0],
            [1, 1],
            [1, 6],
            [1, 7],
            [2, 0],
            [2, 6],
            [2, 7],
            [3, 7],
            [4, 3],
            [4, 7],
            [5, 3],
            [5, 7],
            [6, 0],
            [6, 3],
            [6, 4],
            [7, 0],
            [7, 3],
            [7, 4],
            [8, 0],
            [8, 3],
            [8, 4],
            [8, 5],
            [9, 0],
            [10, 0],
            [10, 1],
            [10, 7],
            [11, 0],
            [11, 1],
            [11, 7],
            [12, 0],
            [12, 1],
            [12, 2],
            [12, 6],
            [12, 7]
        ],

        "flower": [
            0,
            0,
            [5, 3],
            [5, 4],
            [6, 3],
            [6, 4],
            [7, 3],
            [7, 4],
            [8, 3],
            [8, 4],
            [9, 0],
            [9, 1],
            [9, 6],
            [9, 7],
            [10, 0],
            [10, 1],
            [10, 6],
            [10, 7],
            [11, 0],
            [11, 1],
            [11, 6],
            [11, 7],
            [12, 0],
            [12, 1],
            [12, 6],
            [12, 7]
        ]
    }   
}